alaric/__init__.py
alaric/abc/__init__.py
alaric/abc/buildable.py
alaric/abc/comparison.py
alaric/abc/filterable.py
alaric/abc/logical.py
alaric/abc/readme.md
alaric/abc/saveable.py
alaric/advanced_query.py
alaric/cached_document.py
alaric/comparison/__init__.py
alaric/comparison/comparison_eq.py
alaric/comparison/comparison_exists.py
alaric/comparison/comparison_greater_than.py
alaric/comparison/comparison_in.py
alaric/comparison/comparison_less_than.py
alaric/comparison/comparison_regex.py
alaric/comparison/readme.md
alaric/cursor.py
alaric/document.py
alaric/encrypted_document.py
alaric/encryption/__init__.py
alaric/encryption/automatic_hashed_fields.py
alaric/encryption/base.py
alaric/encryption/encrypted_fields.py
alaric/encryption/hashed_fields.py
alaric/encryption/hashed_query_field.py
alaric/encryption/ignore_fields.py
alaric/logical/__init__.py
alaric/logical/logical_and.py
alaric/logical/logical_not.py
alaric/logical/logical_or.py
alaric/logical/readme.md
alaric/meta/__init__.py
alaric/meta/all.py
alaric/meta/case_insensitive.py
alaric/meta/negate.py
alaric/projections/__init__.py
alaric/projections/hide.py
alaric/projections/projections.py
alaric/projections/show.py
alaric/query_builder.py
alaric/types/__init__.py
alaric/types/object_id.py
alaric/util.py
alaric-1.5.0.dist-info/LICENSE
alaric-1.5.0.dist-info/METADATA
alaric-1.5.0.dist-info/WHEEL
alaric-1.5.0.dist-info/RECORD
