Metadata-Version: 2.1
Name: alaric
Version: 1.5.0
Summary: A simplistic yet powerful asynchronous MongoDB query engine.
License: MIT
Author: skelmis
Author-email: skelmis.craft@gmail.com
Requires-Python: >=3.9,<4.0
Classifier: License :: OSI Approved :: MIT License
Classifier: Programming Language :: Python :: 3
Classifier: Programming Language :: Python :: 3.9
Classifier: Programming Language :: Python :: 3.10
Classifier: Programming Language :: Python :: 3.11
Classifier: Programming Language :: Python :: 3.12
Provides-Extra: cached
Requires-Dist: dnspython (>=2.7.0,<3.0.0)
Requires-Dist: motor (>=3.6.0,<4.0.0)
Requires-Dist: orjson (>=3.10.7,<4.0.0)
Requires-Dist: pycryptodome (>=3.21.0,<4.0.0)
Requires-Dist: redis[hiredis] (>=5.1.1,<6.0.0) ; extra == "cached"
